joinly_client/__init__.py
joinly_client/agent.py
joinly_client/client.py
joinly_client/main.py
joinly_client/prompts.py
joinly_client/py.typed
joinly_client/types.py
joinly_client/utils.py
joinly_client-0.1.17.dist-info/METADATA
joinly_client-0.1.17.dist-info/WHEEL
joinly_client-0.1.17.dist-info/entry_points.txt
joinly_client-0.1.17.dist-info/RECORD
