Metadata-Version: 2.4
Name: joinly-client
Version: 0.1.17
Summary: Client for joinly: Make your meetings accessible to AI Agents
Project-URL: Repository, https://github.com/joinly-ai/joinly
Author-email: dbrockmann <dominik@joinly.ai>
Requires-Python: >=3.12
Requires-Dist: click>=8.1.8
Requires-Dist: fastmcp>=2.10.5
Requires-Dist: joinly-common>=0.1.3
Requires-Dist: openai<=1.99.1
Requires-Dist: pydantic-ai-slim[anthropic,google,openai]>=0.4.9
Requires-Dist: python-dotenv>=1.1.0
Requires-Dist: rich>=14.0.0
